{
  "_meta": {
    "fetched_at": "2026-07-15T08:40:24.918Z",
    "source": "cache-pipeline",
    "version": "1.0"
  },
  "global_aqi": {
    "value": 55,
    "unit": "European AQI",
    "year": 2026,
    "source": "Open-Meteo (20 cities avg)"
  },
  "cities": [
    {
      "name": "Sydney",
      "country": "AU",
      "aqi": 19,
      "pm25": 9.6,
      "pm10": 13.4
    },
    {
      "name": "London",
      "country": "GB",
      "aqi": 25,
      "pm25": 5.9,
      "pm10": 10
    },
    {
      "name": "São Paulo",
      "country": "BR",
      "aqi": 27,
      "pm25": 15,
      "pm10": 16.8
    },
    {
      "name": "Berlin",
      "country": "DE",
      "aqi": 28,
      "pm25": 3.9,
      "pm10": 6
    },
    {
      "name": "Paris",
      "country": "FR",
      "aqi": 30,
      "pm25": 8.3,
      "pm10": 12.3
    },
    {
      "name": "Lagos",
      "country": "NG",
      "aqi": 31,
      "pm25": 15.5,
      "pm10": 18.9
    },
    {
      "name": "Los Angeles",
      "country": "US",
      "aqi": 32,
      "pm25": 21,
      "pm10": 23.6
    },
    {
      "name": "New York",
      "country": "US",
      "aqi": 36,
      "pm25": 20.5,
      "pm10": 21.1
    },
    {
      "name": "Istanbul",
      "country": "TR",
      "aqi": 37,
      "pm25": 10.2,
      "pm10": 14.2
    },
    {
      "name": "Cairo",
      "country": "EG",
      "aqi": 44,
      "pm25": 21.2,
      "pm10": 34.2
    },
    {
      "name": "Mumbai",
      "country": "IN",
      "aqi": 50,
      "pm25": 22.3,
      "pm10": 44.7
    },
    {
      "name": "Mexico City",
      "country": "MX",
      "aqi": 55,
      "pm25": 36.2,
      "pm10": 38.1
    },
    {
      "name": "Karachi",
      "country": "PK",
      "aqi": 58,
      "pm25": 23.8,
      "pm10": 58.4
    },
    {
      "name": "Moscow",
      "country": "RU",
      "aqi": 62,
      "pm25": 22.4,
      "pm10": 26
    },
    {
      "name": "Tokyo",
      "country": "JP",
      "aqi": 63,
      "pm25": 29.3,
      "pm10": 35.6
    },
    {
      "name": "Dhaka",
      "country": "BD",
      "aqi": 69,
      "pm25": 21,
      "pm10": 22.1
    },
    {
      "name": "Shanghai",
      "country": "CN",
      "aqi": 73,
      "pm25": 34.9,
      "pm10": 37.3
    },
    {
      "name": "Jakarta",
      "country": "ID",
      "aqi": 95,
      "pm25": 42.6,
      "pm10": 44.6
    },
    {
      "name": "Beijing",
      "country": "CN",
      "aqi": 97,
      "pm25": 37,
      "pm10": 58
    },
    {
      "name": "Delhi",
      "country": "IN",
      "aqi": 167,
      "pm25": 158.3,
      "pm10": 746.9
    }
  ],
  "value": 55
}