{
  "_meta": {
    "fetched_at": "2026-06-14T14:18:22.016Z",
    "source": "cache-pipeline",
    "version": "1.0"
  },
  "conflict_data": {
    "active_conflicts": 59,
    "source": "static_fallback",
    "api_status": "static_fallback",
    "events": [],
    "crises": [],
    "trend_articles": [
      {
        "date": "20260607T150000Z",
        "volume": 20.1563
      },
      {
        "date": "20260607T160000Z",
        "volume": 20.3406
      },
      {
        "date": "20260607T170000Z",
        "volume": 23.5849
      },
      {
        "date": "20260607T190000Z",
        "volume": 20.521
      },
      {
        "date": "20260607T200000Z",
        "volume": 22.0128
      },
      {
        "date": "20260607T210000Z",
        "volume": 24.3088
      },
      {
        "date": "20260607T220000Z",
        "volume": 24.8512
      },
      {
        "date": "20260608T000000Z",
        "volume": 20.9649
      },
      {
        "date": "20260608T010000Z",
        "volume": 21.7227
      },
      {
        "date": "20260608T020000Z",
        "volume": 20.5862
      },
      {
        "date": "20260608T030000Z",
        "volume": 21.2801
      },
      {
        "date": "20260608T040000Z",
        "volume": 19.4318
      },
      {
        "date": "20260608T050000Z",
        "volume": 20.8789
      },
      {
        "date": "20260608T060000Z",
        "volume": 19.27
      },
      {
        "date": "20260608T070000Z",
        "volume": 20.2624
      },
      {
        "date": "20260608T080000Z",
        "volume": 20.698
      },
      {
        "date": "20260608T090000Z",
        "volume": 19.368
      },
      {
        "date": "20260608T100000Z",
        "volume": 17.9499
      },
      {
        "date": "20260608T110000Z",
        "volume": 18.7427
      },
      {
        "date": "20260608T120000Z",
        "volume": 19.0241
      },
      {
        "date": "20260608T130000Z",
        "volume": 19.8473
      },
      {
        "date": "20260608T140000Z",
        "volume": 18.2263
      },
      {
        "date": "20260608T150000Z",
        "volume": 17.2505
      },
      {
        "date": "20260608T160000Z",
        "volume": 16.5975
      },
      {
        "date": "20260608T170000Z",
        "volume": 14.1672
      },
      {
        "date": "20260608T180000Z",
        "volume": 15.8193
      },
      {
        "date": "20260608T190000Z",
        "volume": 16.1145
      },
      {
        "date": "20260608T200000Z",
        "volume": 14.8787
      },
      {
        "date": "20260608T210000Z",
        "volume": 17.3467
      },
      {
        "date": "20260608T220000Z",
        "volume": 19.2252
      },
      {
        "date": "20260608T230000Z",
        "volume": 18.2654
      },
      {
        "date": "20260609T000000Z",
        "volume": 17.2443
      },
      {
        "date": "20260609T010000Z",
        "volume": 17.4493
      },
      {
        "date": "20260609T020000Z",
        "volume": 14.8464
      },
      {
        "date": "20260609T030000Z",
        "volume": 17.2691
      },
      {
        "date": "20260609T040000Z",
        "volume": 17.8682
      },
      {
        "date": "20260609T050000Z",
        "volume": 18.4737
      },
      {
        "date": "20260609T060000Z",
        "volume": 19.4945
      },
      {
        "date": "20260609T070000Z",
        "volume": 19.9646
      },
      {
        "date": "20260609T080000Z",
        "volume": 17.0023
      },
      {
        "date": "20260609T090000Z",
        "volume": 17.3068
      },
      {
        "date": "20260609T100000Z",
        "volume": 17.0236
      },
      {
        "date": "20260609T110000Z",
        "volume": 17.3497
      },
      {
        "date": "20260609T120000Z",
        "volume": 17.5789
      },
      {
        "date": "20260609T130000Z",
        "volume": 18.8804
      },
      {
        "date": "20260609T140000Z",
        "volume": 17.1988
      },
      {
        "date": "20260609T150000Z",
        "volume": 17.9219
      },
      {
        "date": "20260609T160000Z",
        "volume": 16.4821
      },
      {
        "date": "20260609T170000Z",
        "volume": 16.9608
      },
      {
        "date": "20260609T180000Z",
        "volume": 16.7973
      },
      {
        "date": "20260609T190000Z",
        "volume": 17.9665
      },
      {
        "date": "20260609T200000Z",
        "volume": 18.9459
      },
      {
        "date": "20260609T210000Z",
        "volume": 19.4619
      },
      {
        "date": "20260609T220000Z",
        "volume": 19.5362
      },
      {
        "date": "20260609T230000Z",
        "volume": 19.3125
      },
      {
        "date": "20260610T000000Z",
        "volume": 19.9305
      },
      {
        "date": "20260610T010000Z",
        "volume": 21.4233
      },
      {
        "date": "20260610T020000Z",
        "volume": 19.2069
      },
      {
        "date": "20260610T030000Z",
        "volume": 17.7104
      },
      {
        "date": "20260610T040000Z",
        "volume": 19.2943
      },
      {
        "date": "20260610T050000Z",
        "volume": 19.0672
      },
      {
        "date": "20260610T060000Z",
        "volume": 20.521
      },
      {
        "date": "20260610T070000Z",
        "volume": 19.8309
      },
      {
        "date": "20260610T080000Z",
        "volume": 19.7391
      },
      {
        "date": "20260610T090000Z",
        "volume": 18.5816
      },
      {
        "date": "20260610T100000Z",
        "volume": 18.8731
      },
      {
        "date": "20260610T110000Z",
        "volume": 18.3192
      },
      {
        "date": "20260610T120000Z",
        "volume": 18.7456
      },
      {
        "date": "20260610T130000Z",
        "volume": 18.735
      },
      {
        "date": "20260610T140000Z",
        "volume": 18.7447
      },
      {
        "date": "20260610T150000Z",
        "volume": 16.662
      },
      {
        "date": "20260610T160000Z",
        "volume": 18.5286
      },
      {
        "date": "20260610T170000Z",
        "volume": 18.013
      },
      {
        "date": "20260610T180000Z",
        "volume": 17.2175
      },
      {
        "date": "20260610T190000Z",
        "volume": 19.6224
      },
      {
        "date": "20260610T200000Z",
        "volume": 18.5877
      },
      {
        "date": "20260610T210000Z",
        "volume": 18.7996
      },
      {
        "date": "20260610T220000Z",
        "volume": 20.7612
      },
      {
        "date": "20260610T230000Z",
        "volume": 19.8913
      },
      {
        "date": "20260611T000000Z",
        "volume": 21.7551
      },
      {
        "date": "20260611T010000Z",
        "volume": 20.4572
      },
      {
        "date": "20260611T020000Z",
        "volume": 18.692
      },
      {
        "date": "20260611T030000Z",
        "volume": 18.86
      },
      {
        "date": "20260611T040000Z",
        "volume": 18.6335
      },
      {
        "date": "20260611T050000Z",
        "volume": 19.9017
      },
      {
        "date": "20260611T060000Z",
        "volume": 20.3646
      },
      {
        "date": "20260611T070000Z",
        "volume": 20.2773
      },
      {
        "date": "20260611T080000Z",
        "volume": 19.015
      },
      {
        "date": "20260611T090000Z",
        "volume": 20.1664
      },
      {
        "date": "20260611T100000Z",
        "volume": 18.5228
      },
      {
        "date": "20260611T110000Z",
        "volume": 18.0289
      },
      {
        "date": "20260611T120000Z",
        "volume": 18.4614
      },
      {
        "date": "20260611T130000Z",
        "volume": 19.4411
      },
      {
        "date": "20260611T140000Z",
        "volume": 17.6216
      },
      {
        "date": "20260611T150000Z",
        "volume": 17.9122
      },
      {
        "date": "20260611T160000Z",
        "volume": 18.728
      },
      {
        "date": "20260611T170000Z",
        "volume": 18.3103
      },
      {
        "date": "20260611T180000Z",
        "volume": 19.3292
      },
      {
        "date": "20260611T190000Z",
        "volume": 18.3568
      },
      {
        "date": "20260611T200000Z",
        "volume": 20.0163
      },
      {
        "date": "20260611T210000Z",
        "volume": 19.6386
      },
      {
        "date": "20260611T220000Z",
        "volume": 19.7313
      },
      {
        "date": "20260611T230000Z",
        "volume": 17.0525
      },
      {
        "date": "20260612T000000Z",
        "volume": 20.0394
      },
      {
        "date": "20260612T010000Z",
        "volume": 19.3374
      },
      {
        "date": "20260612T020000Z",
        "volume": 17.8339
      },
      {
        "date": "20260612T030000Z",
        "volume": 17.4447
      },
      {
        "date": "20260612T040000Z",
        "volume": 18.1213
      },
      {
        "date": "20260612T050000Z",
        "volume": 17.4063
      },
      {
        "date": "20260612T060000Z",
        "volume": 19.3157
      },
      {
        "date": "20260612T070000Z",
        "volume": 18.6131
      },
      {
        "date": "20260612T080000Z",
        "volume": 18.3165
      },
      {
        "date": "20260612T090000Z",
        "volume": 18.4118
      },
      {
        "date": "20260612T100000Z",
        "volume": 18.5541
      },
      {
        "date": "20260612T110000Z",
        "volume": 16.5405
      },
      {
        "date": "20260612T120000Z",
        "volume": 16.9853
      },
      {
        "date": "20260612T130000Z",
        "volume": 17.6522
      },
      {
        "date": "20260612T140000Z",
        "volume": 17.3161
      },
      {
        "date": "20260612T150000Z",
        "volume": 17.2133
      },
      {
        "date": "20260612T160000Z",
        "volume": 18.5387
      },
      {
        "date": "20260612T170000Z",
        "volume": 18.7471
      },
      {
        "date": "20260612T180000Z",
        "volume": 20.193
      },
      {
        "date": "20260612T190000Z",
        "volume": 19.2173
      },
      {
        "date": "20260612T200000Z",
        "volume": 17.7458
      },
      {
        "date": "20260612T210000Z",
        "volume": 16.5046
      },
      {
        "date": "20260612T220000Z",
        "volume": 16.5251
      },
      {
        "date": "20260612T230000Z",
        "volume": 17.0587
      },
      {
        "date": "20260613T000000Z",
        "volume": 17.0501
      },
      {
        "date": "20260613T010000Z",
        "volume": 17.5275
      },
      {
        "date": "20260613T020000Z",
        "volume": 18.7766
      },
      {
        "date": "20260613T030000Z",
        "volume": 20.8166
      },
      {
        "date": "20260613T040000Z",
        "volume": 18.8723
      },
      {
        "date": "20260613T050000Z",
        "volume": 20.2445
      },
      {
        "date": "20260613T060000Z",
        "volume": 21.6329
      },
      {
        "date": "20260613T070000Z",
        "volume": 20.2882
      },
      {
        "date": "20260613T080000Z",
        "volume": 20.1386
      },
      {
        "date": "20260613T090000Z",
        "volume": 19.2027
      },
      {
        "date": "20260613T100000Z",
        "volume": 18.4954
      },
      {
        "date": "20260613T110000Z",
        "volume": 18.1254
      },
      {
        "date": "20260613T120000Z",
        "volume": 19.951
      },
      {
        "date": "20260613T130000Z",
        "volume": 20.0541
      },
      {
        "date": "20260613T140000Z",
        "volume": 20.2589
      },
      {
        "date": "20260613T150000Z",
        "volume": 19.4761
      },
      {
        "date": "20260613T160000Z",
        "volume": 19.6712
      },
      {
        "date": "20260613T170000Z",
        "volume": 19.5926
      },
      {
        "date": "20260613T180000Z",
        "volume": 19.2777
      },
      {
        "date": "20260613T190000Z",
        "volume": 20.1104
      },
      {
        "date": "20260613T200000Z",
        "volume": 19.4883
      },
      {
        "date": "20260613T210000Z",
        "volume": 20.0652
      },
      {
        "date": "20260613T220000Z",
        "volume": 20.3675
      },
      {
        "date": "20260613T230000Z",
        "volume": 19.2784
      },
      {
        "date": "20260614T000000Z",
        "volume": 20.5902
      },
      {
        "date": "20260614T010000Z",
        "volume": 19.4053
      },
      {
        "date": "20260614T020000Z",
        "volume": 20.3068
      },
      {
        "date": "20260614T030000Z",
        "volume": 19.6267
      },
      {
        "date": "20260614T040000Z",
        "volume": 17.7425
      },
      {
        "date": "20260614T050000Z",
        "volume": 20.4558
      },
      {
        "date": "20260614T060000Z",
        "volume": 21.5137
      },
      {
        "date": "20260614T070000Z",
        "volume": 20.4754
      },
      {
        "date": "20260614T080000Z",
        "volume": 20.9483
      },
      {
        "date": "20260614T090000Z",
        "volume": 22.5472
      },
      {
        "date": "20260614T100000Z",
        "volume": 20.8971
      },
      {
        "date": "20260614T110000Z",
        "volume": 20.9356
      },
      {
        "date": "20260614T120000Z",
        "volume": 21.0681
      },
      {
        "date": "20260614T130000Z",
        "volume": 20.4875
      }
    ],
    "acled": null
  }
}