{
  "_meta": {
    "fetched_at": "2026-03-23T06:49:06.450Z",
    "source": "cache-pipeline",
    "version": "1.0"
  },
  "disasters": [
    {
      "name": "Myanmar - Cyclone Mocha",
      "date": "2024-05-14",
      "type": "Cyclone",
      "countries": [
        "Myanmar"
      ],
      "status": "past"
    },
    {
      "name": "Libya - Floods",
      "date": "2024-09-10",
      "type": "Flood",
      "countries": [
        "Libya"
      ],
      "status": "past"
    },
    {
      "name": "Morocco - Earthquake",
      "date": "2024-09-08",
      "type": "Earthquake",
      "countries": [
        "Morocco"
      ],
      "status": "past"
    },
    {
      "name": "Turkiye - Syria Earthquake",
      "date": "2024-02-06",
      "type": "Earthquake",
      "countries": [
        "Turkiye",
        "Syrian Arab Republic"
      ],
      "status": "past"
    },
    {
      "name": "Pakistan - Floods",
      "date": "2024-08-15",
      "type": "Flood",
      "countries": [
        "Pakistan"
      ],
      "status": "past"
    },
    {
      "name": "Afghanistan - Earthquake",
      "date": "2024-10-07",
      "type": "Earthquake",
      "countries": [
        "Afghanistan"
      ],
      "status": "past"
    },
    {
      "name": "Philippines - Typhoon Rai",
      "date": "2024-12-16",
      "type": "Cyclone",
      "countries": [
        "Philippines"
      ],
      "status": "past"
    },
    {
      "name": "East Africa - Drought",
      "date": "2024-01-01",
      "type": "Drought",
      "countries": [
        "Somalia",
        "Ethiopia",
        "Kenya"
      ],
      "status": "ongoing"
    },
    {
      "name": "Sudan - Conflict",
      "date": "2024-04-15",
      "type": "Complex Emergency",
      "countries": [
        "Sudan"
      ],
      "status": "ongoing"
    },
    {
      "name": "Ukraine - Conflict",
      "date": "2024-02-24",
      "type": "Complex Emergency",
      "countries": [
        "Ukraine"
      ],
      "status": "ongoing"
    }
  ],
  "api_status": "static_fallback",
  "note": "Static fallback -- ReliefWeb API requires registered appname since 2026"
}