{
  "_meta": {
    "fetched_at": "2026-06-16T21:11:20.180Z",
    "source": "cache-pipeline",
    "version": "1.0"
  },
  "significant_24h": {
    "value": 26,
    "year": 2026,
    "source": "USGS (M4.5+ last 24h)"
  },
  "magnitude_5_plus_7d": {
    "value": 42,
    "year": 2026,
    "source": "USGS (M5+ last 7d)"
  },
  "significant_24h_events": [
    {
      "id": "us7000stfx",
      "mag": 4.8,
      "place": "52 km WNW of Poso, Indonesia",
      "time": "2026-06-16T18:29:37.606Z",
      "url": "https://earthquake.usgs.gov/earthquakes/eventpage/us7000stfx",
      "tsunami": false,
      "depth_km": 10,
      "lon": 120.3052,
      "lat": -1.233
    },
    {
      "id": "us7000stfq",
      "mag": 4.5,
      "place": "139 km ESE of Pondaguitan, Philippines",
      "time": "2026-06-16T17:51:17.894Z",
      "url": "https://earthquake.usgs.gov/earthquakes/eventpage/us7000stfq",
      "tsunami": false,
      "depth_km": 10,
      "lon": 127.2277,
      "lat": 5.6628
    },
    {
      "id": "us7000stff",
      "mag": 4.5,
      "place": "97 km ENE of Miyako, Japan",
      "time": "2026-06-16T17:25:57.600Z",
      "url": "https://earthquake.usgs.gov/earthquakes/eventpage/us7000stff",
      "tsunami": false,
      "depth_km": 35,
      "lon": 143.0218,
      "lat": 39.9143
    },
    {
      "id": "us7000stf7",
      "mag": 4.8,
      "place": "South Sandwich Islands region",
      "time": "2026-06-16T17:13:10.014Z",
      "url": "https://earthquake.usgs.gov/earthquakes/eventpage/us7000stf7",
      "tsunami": false,
      "depth_km": 21.841,
      "lon": -26.336,
      "lat": -55.8718
    },
    {
      "id": "us7000stea",
      "mag": 4.5,
      "place": "32 km W of Titahi Bay, New Zealand",
      "time": "2026-06-16T14:33:08.719Z",
      "url": "https://earthquake.usgs.gov/earthquakes/eventpage/us7000stea",
      "tsunami": false,
      "depth_km": 73.245,
      "lon": 174.445,
      "lat": -41.062
    },
    {
      "id": "us7000ste2",
      "mag": 4.9,
      "place": "256 km SSE of Dunhuang, China",
      "time": "2026-06-16T13:27:36.651Z",
      "url": "https://earthquake.usgs.gov/earthquakes/eventpage/us7000ste2",
      "tsunami": false,
      "depth_km": 12.517,
      "lon": 95.2912,
      "lat": 37.9084
    },
    {
      "id": "us7000stdz",
      "mag": 4.8,
      "place": "65 km S of Kokopo, Papua New Guinea",
      "time": "2026-06-16T13:03:41.301Z",
      "url": "https://earthquake.usgs.gov/earthquakes/eventpage/us7000stdz",
      "tsunami": false,
      "depth_km": 66.484,
      "lon": 152.3659,
      "lat": -4.9284
    },
    {
      "id": "us7000stdf",
      "mag": 4.8,
      "place": "southeast central Pacific Ocean",
      "time": "2026-06-16T11:30:32.628Z",
      "url": "https://earthquake.usgs.gov/earthquakes/eventpage/us7000stdf",
      "tsunami": false,
      "depth_km": 10,
      "lon": -82.7806,
      "lat": -36.3224
    },
    {
      "id": "us7000stdb",
      "mag": 5,
      "place": "261 km SSE of Dunhuang, China",
      "time": "2026-06-16T11:14:17.721Z",
      "url": "https://earthquake.usgs.gov/earthquakes/eventpage/us7000stdb",
      "tsunami": false,
      "depth_km": 10,
      "lon": 95.4313,
      "lat": 37.8819
    },
    {
      "id": "us7000stdg",
      "mag": 4.8,
      "place": "52 km SE of Palu, Indonesia",
      "time": "2026-06-16T11:03:52.442Z",
      "url": "https://earthquake.usgs.gov/earthquakes/eventpage/us7000stdg",
      "tsunami": false,
      "depth_km": 10,
      "lon": 120.2174,
      "lat": -1.2294
    },
    {
      "id": "us7000std9",
      "mag": 4.7,
      "place": "248 km SSE of Dunhuang, China",
      "time": "2026-06-16T11:01:02.008Z",
      "url": "https://earthquake.usgs.gov/earthquakes/eventpage/us7000std9",
      "tsunami": false,
      "depth_km": 10,
      "lon": 95.2704,
      "lat": 37.9792
    },
    {
      "id": "us7000std7",
      "mag": 5.5,
      "place": "4 km NW of Noda, Japan",
      "time": "2026-06-16T10:46:34.658Z",
      "url": "https://earthquake.usgs.gov/earthquakes/eventpage/us7000std7",
      "tsunami": false,
      "depth_km": 71.777,
      "lon": 139.8371,
      "lat": 35.9814
    },
    {
      "id": "us7000std4",
      "mag": 4.8,
      "place": "90 km WSW of Ternate, Indonesia",
      "time": "2026-06-16T10:23:50.862Z",
      "url": "https://earthquake.usgs.gov/earthquakes/eventpage/us7000std4",
      "tsunami": false,
      "depth_km": 52.503,
      "lon": 126.6007,
      "lat": 0.5717
    },
    {
      "id": "us7000stcs",
      "mag": 5.4,
      "place": "277 km S of Dunhuang, China",
      "time": "2026-06-16T09:45:26.434Z",
      "url": "https://earthquake.usgs.gov/earthquakes/eventpage/us7000stcs",
      "tsunami": false,
      "depth_km": 10,
      "lon": 95.2125,
      "lat": 37.6989
    },
    {
      "id": "us7000std2",
      "mag": 5.2,
      "place": "242 km SSE of Dunhuang, China",
      "time": "2026-06-16T09:42:35.214Z",
      "url": "https://earthquake.usgs.gov/earthquakes/eventpage/us7000std2",
      "tsunami": false,
      "depth_km": 10,
      "lon": 95.4312,
      "lat": 38.0579
    },
    {
      "id": "us7000stbz",
      "mag": 6.3,
      "place": "260 km SSE of Dunhuang, China",
      "time": "2026-06-16T09:06:55.226Z",
      "url": "https://earthquake.usgs.gov/earthquakes/eventpage/us7000stbz",
      "tsunami": false,
      "depth_km": 10,
      "lon": 95.4028,
      "lat": 37.8888
    },
    {
      "id": "us7000stbw",
      "mag": 4.6,
      "place": "17 km SE of Viqueque, Timor Leste",
      "time": "2026-06-16T09:03:43.900Z",
      "url": "https://earthquake.usgs.gov/earthquakes/eventpage/us7000stbw",
      "tsunami": false,
      "depth_km": 10,
      "lon": 126.4947,
      "lat": -8.9506
    },
    {
      "id": "us7000stbp",
      "mag": 5,
      "place": "49 km ESE of Palu, Indonesia",
      "time": "2026-06-16T08:04:46.472Z",
      "url": "https://earthquake.usgs.gov/earthquakes/eventpage/us7000stbp",
      "tsunami": false,
      "depth_km": 48.869,
      "lon": 120.2567,
      "lat": -1.1234
    },
    {
      "id": "us7000staz",
      "mag": 4.7,
      "place": "14 km SSW of Balangonan, Philippines",
      "time": "2026-06-16T05:44:05.058Z",
      "url": "https://earthquake.usgs.gov/earthquakes/eventpage/us7000staz",
      "tsunami": false,
      "depth_km": 92.946,
      "lon": 125.3137,
      "lat": 5.4475
    },
    {
      "id": "us7000sta1",
      "mag": 5.1,
      "place": "49 km SE of Palu, Indonesia",
      "time": "2026-06-16T04:14:01.591Z",
      "url": "https://earthquake.usgs.gov/earthquakes/eventpage/us7000sta1",
      "tsunami": false,
      "depth_km": 10,
      "lon": 120.2257,
      "lat": -1.1746
    }
  ],
  "significant_week_events": [
    {
      "id": "us7000stbz",
      "mag": 6.3,
      "place": "260 km SSE of Dunhuang, China",
      "time": "2026-06-16T09:06:55.226Z",
      "url": "https://earthquake.usgs.gov/earthquakes/eventpage/us7000stbz",
      "tsunami": false,
      "depth_km": 10,
      "lon": 95.4028,
      "lat": 37.8888
    },
    {
      "id": "us7000st95",
      "mag": 6.7,
      "place": "43 km ESE of Palu, Indonesia",
      "time": "2026-06-16T03:27:44.418Z",
      "url": "https://earthquake.usgs.gov/earthquakes/eventpage/us7000st95",
      "tsunami": false,
      "depth_km": 10,
      "lon": 120.199,
      "lat": -1.1173
    },
    {
      "id": "us7000st41",
      "mag": 2.4,
      "place": "8 km NE of Bel Air North, Maryland",
      "time": "2026-06-15T15:02:24.147Z",
      "url": "https://earthquake.usgs.gov/earthquakes/eventpage/us7000st41",
      "tsunami": false,
      "depth_km": 5,
      "lon": -76.3097,
      "lat": 39.6174
    },
    {
      "id": "hv74978947",
      "mag": 4.71,
      "place": "23 km E of Pāpa‘ikou, Hawaii",
      "time": "2026-06-10T08:37:40.490Z",
      "url": "https://earthquake.usgs.gov/earthquakes/eventpage/hv74978947",
      "tsunami": false,
      "depth_km": 39.18,
      "lon": -154.866166666667,
      "lat": 19.7843333333333
    }
  ]
}