{
  "_meta": {
    "fetched_at": "2026-06-07T19:43:39.480Z",
    "source": "cache-pipeline",
    "version": "1.0"
  },
  "significant_24h": {
    "value": 17,
    "year": 2026,
    "source": "USGS (M4.5+ last 24h)"
  },
  "magnitude_5_plus_7d": {
    "value": 30,
    "year": 2026,
    "source": "USGS (M5+ last 7d)"
  },
  "significant_24h_events": [
    {
      "id": "us7000sr9u",
      "mag": 4.7,
      "place": "off the coast of Central America",
      "time": "2026-06-07T18:22:06.925Z",
      "url": "https://earthquake.usgs.gov/earthquakes/eventpage/us7000sr9u",
      "tsunami": false,
      "depth_km": 10,
      "lon": -84.6908,
      "lat": 2.0593
    },
    {
      "id": "us7000sr9r",
      "mag": 5.8,
      "place": "Easter Island region",
      "time": "2026-06-07T18:01:20.966Z",
      "url": "https://earthquake.usgs.gov/earthquakes/eventpage/us7000sr9r",
      "tsunami": false,
      "depth_km": 10,
      "lon": -112.2108,
      "lat": -29.1847
    },
    {
      "id": "us7000sr9n",
      "mag": 4.6,
      "place": "120 km SE of Severo-Kuril’sk, Russia",
      "time": "2026-06-07T17:54:36.071Z",
      "url": "https://earthquake.usgs.gov/earthquakes/eventpage/us7000sr9n",
      "tsunami": false,
      "depth_km": 35,
      "lon": 157.4645,
      "lat": 50.0122
    },
    {
      "id": "us7000sr9l",
      "mag": 4.5,
      "place": "south of the Fiji Islands",
      "time": "2026-06-07T17:47:39.457Z",
      "url": "https://earthquake.usgs.gov/earthquakes/eventpage/us7000sr9l",
      "tsunami": false,
      "depth_km": 516.817,
      "lon": 179.8177,
      "lat": -25.1179
    },
    {
      "id": "us7000sr9s",
      "mag": 4.5,
      "place": "185 km ESE of Severo-Kuril’sk, Russia",
      "time": "2026-06-07T17:38:02.926Z",
      "url": "https://earthquake.usgs.gov/earthquakes/eventpage/us7000sr9s",
      "tsunami": false,
      "depth_km": 10,
      "lon": 158.5609,
      "lat": 50.0857
    },
    {
      "id": "us7000sr9j",
      "mag": 5.6,
      "place": "15 km WNW of Punākha, Bhutan",
      "time": "2026-06-07T17:36:39.953Z",
      "url": "https://earthquake.usgs.gov/earthquakes/eventpage/us7000sr9j",
      "tsunami": false,
      "depth_km": 10,
      "lon": 89.7236,
      "lat": 27.6243
    },
    {
      "id": "us7000sr8v",
      "mag": 5.5,
      "place": "139 km SE of Severo-Kuril’sk, Russia",
      "time": "2026-06-07T14:53:56.180Z",
      "url": "https://earthquake.usgs.gov/earthquakes/eventpage/us7000sr8v",
      "tsunami": false,
      "depth_km": 10,
      "lon": 157.6645,
      "lat": 49.8979
    },
    {
      "id": "us7000sr8k",
      "mag": 4.6,
      "place": "70 km W of San Antonio de los Cobres, Argentina",
      "time": "2026-06-07T13:57:18.086Z",
      "url": "https://earthquake.usgs.gov/earthquakes/eventpage/us7000sr8k",
      "tsunami": false,
      "depth_km": 182.14,
      "lon": -67.0098,
      "lat": -24.2434
    },
    {
      "id": "us7000sr8i",
      "mag": 4.6,
      "place": "Izu Islands, Japan region",
      "time": "2026-06-07T13:36:50.223Z",
      "url": "https://earthquake.usgs.gov/earthquakes/eventpage/us7000sr8i",
      "tsunami": false,
      "depth_km": 10,
      "lon": 141.971,
      "lat": 30.6675
    },
    {
      "id": "us7000sr8g",
      "mag": 4.7,
      "place": "168 km SSW of Bengkulu, Indonesia",
      "time": "2026-06-07T13:31:46.524Z",
      "url": "https://earthquake.usgs.gov/earthquakes/eventpage/us7000sr8g",
      "tsunami": false,
      "depth_km": 10,
      "lon": 101.5557,
      "lat": -5.1466
    },
    {
      "id": "us7000sr8c",
      "mag": 4.6,
      "place": "29 km WNW of Sinabang, Indonesia",
      "time": "2026-06-07T13:06:10.958Z",
      "url": "https://earthquake.usgs.gov/earthquakes/eventpage/us7000sr8c",
      "tsunami": false,
      "depth_km": 26.408,
      "lon": 96.1308,
      "lat": 2.5731
    },
    {
      "id": "us7000sr7l",
      "mag": 6.1,
      "place": "124 km SE of Severo-Kuril’sk, Russia",
      "time": "2026-06-07T10:41:58.596Z",
      "url": "https://earthquake.usgs.gov/earthquakes/eventpage/us7000sr7l",
      "tsunami": false,
      "depth_km": 35,
      "lon": 157.3799,
      "lat": 49.8993
    },
    {
      "id": "us7000sr7d",
      "mag": 5.2,
      "place": "7 km W of Prokópi, Greece",
      "time": "2026-06-07T10:02:48.827Z",
      "url": "https://earthquake.usgs.gov/earthquakes/eventpage/us7000sr7d",
      "tsunami": false,
      "depth_km": 10,
      "lon": 23.4046,
      "lat": 38.7304
    },
    {
      "id": "us7000sr7c",
      "mag": 4.9,
      "place": "5 km ENE of Límni, Greece",
      "time": "2026-06-07T09:58:45.829Z",
      "url": "https://earthquake.usgs.gov/earthquakes/eventpage/us7000sr7c",
      "tsunami": false,
      "depth_km": 10,
      "lon": 23.3819,
      "lat": 38.7777
    },
    {
      "id": "us7000sr6c",
      "mag": 5.4,
      "place": "south of the Fiji Islands",
      "time": "2026-06-07T03:56:57.053Z",
      "url": "https://earthquake.usgs.gov/earthquakes/eventpage/us7000sr6c",
      "tsunami": false,
      "depth_km": 506.648,
      "lon": -179.849,
      "lat": -24.3729
    },
    {
      "id": "us7000sr64",
      "mag": 5.1,
      "place": "196 km NE of Lospalos, Timor Leste",
      "time": "2026-06-07T02:53:05.880Z",
      "url": "https://earthquake.usgs.gov/earthquakes/eventpage/us7000sr64",
      "tsunami": false,
      "depth_km": 161.221,
      "lon": 128.439,
      "lat": -7.4742
    },
    {
      "id": "us7000sr5i",
      "mag": 5.2,
      "place": "22 km E of Venilale, Timor Leste",
      "time": "2026-06-06T22:38:35.829Z",
      "url": "https://earthquake.usgs.gov/earthquakes/eventpage/us7000sr5i",
      "tsunami": false,
      "depth_km": 10,
      "lon": 126.5825,
      "lat": -8.6648
    }
  ],
  "significant_week_events": [
    {
      "id": "nn00919749",
      "mag": 3.75,
      "place": "11 km NW of Summerlin South, Nevada",
      "time": "2026-06-04T20:47:58.995Z",
      "url": "https://earthquake.usgs.gov/earthquakes/eventpage/nn00919749",
      "tsunami": false,
      "depth_km": 7,
      "lon": -115.4319,
      "lat": 36.1764
    },
    {
      "id": "hv74975297",
      "mag": 4.57,
      "place": "6 km WNW of Kahaluu-Keauhou, Hawaii",
      "time": "2026-06-03T03:58:53.210Z",
      "url": "https://earthquake.usgs.gov/earthquakes/eventpage/hv74975297",
      "tsunami": false,
      "depth_km": 34.01,
      "lon": -156.016333333333,
      "lat": 19.5881666666667
    },
    {
      "id": "us7000spxm",
      "mag": 6.2,
      "place": "22 km WSW of Scarcelli, Italy",
      "time": "2026-06-01T22:12:36.284Z",
      "url": "https://earthquake.usgs.gov/earthquakes/eventpage/us7000spxm",
      "tsunami": false,
      "depth_km": 243,
      "lon": 15.7796,
      "lat": 39.325
    },
    {
      "id": "us7000spqc",
      "mag": 6,
      "place": "33 km NW of Valparaíso, Chile",
      "time": "2026-05-31T21:34:18.026Z",
      "url": "https://earthquake.usgs.gov/earthquakes/eventpage/us7000spqc",
      "tsunami": false,
      "depth_km": 25,
      "lon": -71.8593,
      "lat": -32.8047
    }
  ]
}