{
  "_meta": {
    "fetched_at": "2026-06-10T04:16:18.962Z",
    "source": "cache-pipeline",
    "version": "1.0"
  },
  "significant_24h": {
    "value": 21,
    "year": 2026,
    "source": "USGS (M4.5+ last 24h)"
  },
  "magnitude_5_plus_7d": {
    "value": 61,
    "year": 2026,
    "source": "USGS (M5+ last 7d)"
  },
  "significant_24h_events": [
    {
      "id": "us7000sry7",
      "mag": 5.1,
      "place": "11 km WSW of Sardinal, Costa Rica",
      "time": "2026-06-10T03:01:35.137Z",
      "url": "https://earthquake.usgs.gov/earthquakes/eventpage/us7000sry7",
      "tsunami": false,
      "depth_km": 64.993,
      "lon": -85.7378,
      "lat": 10.4644
    },
    {
      "id": "us7000sry1",
      "mag": 5,
      "place": "6 km WSW of Burias, Philippines",
      "time": "2026-06-10T01:54:24.466Z",
      "url": "https://earthquake.usgs.gov/earthquakes/eventpage/us7000sry1",
      "tsunami": false,
      "depth_km": 89.605,
      "lon": 125.1975,
      "lat": 5.697
    },
    {
      "id": "us7000srxn",
      "mag": 6,
      "place": "Auckland Islands, New Zealand region",
      "time": "2026-06-10T00:44:21.127Z",
      "url": "https://earthquake.usgs.gov/earthquakes/eventpage/us7000srxn",
      "tsunami": false,
      "depth_km": 13.669,
      "lon": 164.0984,
      "lat": -49.6197
    },
    {
      "id": "us7000srxm",
      "mag": 4.6,
      "place": "66 km SE of Shikotan, Russia",
      "time": "2026-06-10T00:28:58.921Z",
      "url": "https://earthquake.usgs.gov/earthquakes/eventpage/us7000srxm",
      "tsunami": false,
      "depth_km": 35,
      "lon": 147.4046,
      "lat": 43.4617
    },
    {
      "id": "us7000srxa",
      "mag": 4.8,
      "place": "8 km SSW of Sarangani, Philippines",
      "time": "2026-06-09T23:14:43.247Z",
      "url": "https://earthquake.usgs.gov/earthquakes/eventpage/us7000srxa",
      "tsunami": false,
      "depth_km": 62.776,
      "lon": 125.429,
      "lat": 5.3342
    },
    {
      "id": "us7000srwv",
      "mag": 4.6,
      "place": "south of the Kermadec Islands",
      "time": "2026-06-09T21:23:46.112Z",
      "url": "https://earthquake.usgs.gov/earthquakes/eventpage/us7000srwv",
      "tsunami": false,
      "depth_km": 388.027,
      "lon": -179.7655,
      "lat": -32.0388
    },
    {
      "id": "us7000srvv",
      "mag": 5.2,
      "place": "163 km ESE of Petropavlovsk-Kamchatsky, Russia",
      "time": "2026-06-09T19:49:03.951Z",
      "url": "https://earthquake.usgs.gov/earthquakes/eventpage/us7000srvv",
      "tsunami": false,
      "depth_km": 10,
      "lon": 160.7499,
      "lat": 52.3674
    },
    {
      "id": "us7000srvn",
      "mag": 5.1,
      "place": "southeast Indian Ridge",
      "time": "2026-06-09T19:36:10.562Z",
      "url": "https://earthquake.usgs.gov/earthquakes/eventpage/us7000srvn",
      "tsunami": false,
      "depth_km": 10,
      "lon": 84.9096,
      "lat": -41.5157
    },
    {
      "id": "us7000srvk",
      "mag": 5.1,
      "place": "120 km ESE of Kuril’sk, Russia",
      "time": "2026-06-09T19:25:35.189Z",
      "url": "https://earthquake.usgs.gov/earthquakes/eventpage/us7000srvk",
      "tsunami": false,
      "depth_km": 56.076,
      "lon": 149.2865,
      "lat": 44.8123
    },
    {
      "id": "us7000srun",
      "mag": 5,
      "place": "8 km SW of Taluya, Philippines",
      "time": "2026-06-09T18:09:52.935Z",
      "url": "https://earthquake.usgs.gov/earthquakes/eventpage/us7000srun",
      "tsunami": false,
      "depth_km": 35,
      "lon": 125.1164,
      "lat": 5.766
    },
    {
      "id": "us7000srul",
      "mag": 4.5,
      "place": "222 km SE of Pondaguitan, Philippines",
      "time": "2026-06-09T17:51:42.066Z",
      "url": "https://earthquake.usgs.gov/earthquakes/eventpage/us7000srul",
      "tsunami": false,
      "depth_km": 35,
      "lon": 127.5632,
      "lat": 4.9069
    },
    {
      "id": "us7000sruf",
      "mag": 5.1,
      "place": "65 km SSW of Sarangani, Philippines",
      "time": "2026-06-09T17:40:37.238Z",
      "url": "https://earthquake.usgs.gov/earthquakes/eventpage/us7000sruf",
      "tsunami": false,
      "depth_km": 36.209,
      "lon": 125.2852,
      "lat": 4.8395
    },
    {
      "id": "us7000sru0",
      "mag": 5.1,
      "place": "4 km SSW of Bukid, Philippines",
      "time": "2026-06-09T16:49:24.753Z",
      "url": "https://earthquake.usgs.gov/earthquakes/eventpage/us7000sru0",
      "tsunami": false,
      "depth_km": 59.19,
      "lon": 125.3855,
      "lat": 5.5352
    },
    {
      "id": "us7000srub",
      "mag": 4.9,
      "place": "Pagan region, Northern Mariana Islands",
      "time": "2026-06-09T16:48:51.184Z",
      "url": "https://earthquake.usgs.gov/earthquakes/eventpage/us7000srub",
      "tsunami": false,
      "depth_km": 51.723,
      "lon": 146.57,
      "lat": 18.5538
    },
    {
      "id": "us7000srqm",
      "mag": 4.7,
      "place": "28 km S of Sarangani, Philippines",
      "time": "2026-06-09T12:55:05.541Z",
      "url": "https://earthquake.usgs.gov/earthquakes/eventpage/us7000srqm",
      "tsunami": false,
      "depth_km": 54.666,
      "lon": 125.4513,
      "lat": 5.1489
    },
    {
      "id": "us7000srq8",
      "mag": 4.8,
      "place": "north of Ascension Island",
      "time": "2026-06-09T11:17:38.741Z",
      "url": "https://earthquake.usgs.gov/earthquakes/eventpage/us7000srq8",
      "tsunami": false,
      "depth_km": 10,
      "lon": -14.8752,
      "lat": -1.3003
    },
    {
      "id": "us7000srpu",
      "mag": 5.4,
      "place": "21 km SSW of Lumatil, Philippines",
      "time": "2026-06-09T10:07:29.185Z",
      "url": "https://earthquake.usgs.gov/earthquakes/eventpage/us7000srpu",
      "tsunami": false,
      "depth_km": 35,
      "lon": 124.825,
      "lat": 5.6881
    },
    {
      "id": "us7000srpr",
      "mag": 5.1,
      "place": "6 km SSW of Sibagat, Philippines",
      "time": "2026-06-09T09:24:58.682Z",
      "url": "https://earthquake.usgs.gov/earthquakes/eventpage/us7000srpr",
      "tsunami": false,
      "depth_km": 10,
      "lon": 125.685,
      "lat": 8.769
    },
    {
      "id": "us7000srpn",
      "mag": 4.8,
      "place": "116 km SW of Tambolaka, Indonesia",
      "time": "2026-06-09T09:03:58.471Z",
      "url": "https://earthquake.usgs.gov/earthquakes/eventpage/us7000srpn",
      "tsunami": false,
      "depth_km": 24.483,
      "lon": 118.5847,
      "lat": -10.262
    },
    {
      "id": "us7000srph",
      "mag": 4.9,
      "place": "2 km ESE of Nuing, Philippines",
      "time": "2026-06-09T08:15:35.103Z",
      "url": "https://earthquake.usgs.gov/earthquakes/eventpage/us7000srph",
      "tsunami": false,
      "depth_km": 50.122,
      "lon": 125.4582,
      "lat": 5.622
    }
  ],
  "significant_week_events": [
    {
      "id": "us7000srjx",
      "mag": 6.1,
      "place": "102 km WNW of Mantua, Cuba",
      "time": "2026-06-08T18:00:27.508Z",
      "url": "https://earthquake.usgs.gov/earthquakes/eventpage/us7000srjx",
      "tsunami": false,
      "depth_km": 26,
      "lon": -85.1254,
      "lat": 22.7854
    },
    {
      "id": "us7000srcg",
      "mag": 6.5,
      "place": "20 km WSW of Balangonan, Philippines",
      "time": "2026-06-08T00:55:11.958Z",
      "url": "https://earthquake.usgs.gov/earthquakes/eventpage/us7000srcg",
      "tsunami": false,
      "depth_km": 69.004,
      "lon": 125.1951,
      "lat": 5.4762
    },
    {
      "id": "us7000srb1",
      "mag": 7.8,
      "place": "26 km SW of Kablalan, Philippines",
      "time": "2026-06-07T23:37:41.803Z",
      "url": "https://earthquake.usgs.gov/earthquakes/eventpage/us7000srb1",
      "tsunami": false,
      "depth_km": 55.193,
      "lon": 125.0469,
      "lat": 5.5918
    },
    {
      "id": "nn00919749",
      "mag": 3.75,
      "place": "11 km NW of Summerlin South, Nevada",
      "time": "2026-06-04T20:47:58.995Z",
      "url": "https://earthquake.usgs.gov/earthquakes/eventpage/nn00919749",
      "tsunami": false,
      "depth_km": 7,
      "lon": -115.4319,
      "lat": 36.1764
    }
  ]
}