{
  "_meta": {
    "fetched_at": "2026-07-05T19:34:32.895Z",
    "source": "cache-pipeline",
    "version": "1.0"
  },
  "significant_24h": {
    "value": 12,
    "year": 2026,
    "source": "USGS (M4.5+ last 24h)"
  },
  "magnitude_5_plus_7d": {
    "value": 37,
    "year": 2026,
    "source": "USGS (M5+ last 7d)"
  },
  "significant_24h_events": [
    {
      "id": "us6000tab5",
      "mag": 4.6,
      "place": "185 km W of Abepura, Indonesia",
      "time": "2026-07-05T19:10:14.439Z",
      "url": "https://earthquake.usgs.gov/earthquakes/eventpage/us6000tab5",
      "tsunami": false,
      "depth_km": 19.39,
      "lon": 138.968,
      "lat": -2.7128
    },
    {
      "id": "us6000taab",
      "mag": 5,
      "place": "106 km NW of Coquimbo, Chile",
      "time": "2026-07-05T15:53:33.718Z",
      "url": "https://earthquake.usgs.gov/earthquakes/eventpage/us6000taab",
      "tsunami": false,
      "depth_km": 10,
      "lon": -72.0113,
      "lat": -29.1964
    },
    {
      "id": "us6000taaa",
      "mag": 5,
      "place": "26 km NNW of Mianzhu, Deyang, Sichuan, China",
      "time": "2026-07-05T15:30:13.631Z",
      "url": "https://earthquake.usgs.gov/earthquakes/eventpage/us6000taaa",
      "tsunami": false,
      "depth_km": 10,
      "lon": 104.126,
      "lat": 31.5649
    },
    {
      "id": "us6000taa2",
      "mag": 5,
      "place": "23 km NNW of Mianzhu, Deyang, Sichuan, China",
      "time": "2026-07-05T15:03:27.206Z",
      "url": "https://earthquake.usgs.gov/earthquakes/eventpage/us6000taa2",
      "tsunami": false,
      "depth_km": 10,
      "lon": 104.0978,
      "lat": 31.5223
    },
    {
      "id": "us6000ta9n",
      "mag": 5,
      "place": "98 km NW of Coquimbo, Chile",
      "time": "2026-07-05T14:42:04.314Z",
      "url": "https://earthquake.usgs.gov/earthquakes/eventpage/us6000ta9n",
      "tsunami": false,
      "depth_km": 10,
      "lon": -71.9385,
      "lat": -29.2333
    },
    {
      "id": "us6000ta9m",
      "mag": 5.8,
      "place": "274 km SE of Levuka, Fiji",
      "time": "2026-07-05T14:22:26.034Z",
      "url": "https://earthquake.usgs.gov/earthquakes/eventpage/us6000ta9m",
      "tsunami": false,
      "depth_km": 685.692,
      "lon": -179.03,
      "lat": -19.9807
    },
    {
      "id": "us6000ta95",
      "mag": 4.5,
      "place": "71 km W of Ovalle, Chile",
      "time": "2026-07-05T11:57:27.433Z",
      "url": "https://earthquake.usgs.gov/earthquakes/eventpage/us6000ta95",
      "tsunami": false,
      "depth_km": 17.675,
      "lon": -71.9367,
      "lat": -30.6592
    },
    {
      "id": "us6000ta86",
      "mag": 5.3,
      "place": "71 km S of Severo-Kuril’sk, Russia",
      "time": "2026-07-05T07:37:07.006Z",
      "url": "https://earthquake.usgs.gov/earthquakes/eventpage/us6000ta86",
      "tsunami": false,
      "depth_km": 82.936,
      "lon": 156.0014,
      "lat": 50.0397
    },
    {
      "id": "us6000ta6r",
      "mag": 4.5,
      "place": "south of the Fiji Islands",
      "time": "2026-07-04T23:51:03.012Z",
      "url": "https://earthquake.usgs.gov/earthquakes/eventpage/us6000ta6r",
      "tsunami": false,
      "depth_km": 531.576,
      "lon": 179.3801,
      "lat": -24.9821
    },
    {
      "id": "us6000ta6j",
      "mag": 4.5,
      "place": "Fiji region",
      "time": "2026-07-04T22:26:56.558Z",
      "url": "https://earthquake.usgs.gov/earthquakes/eventpage/us6000ta6j",
      "tsunami": false,
      "depth_km": 624.485,
      "lon": -179.2395,
      "lat": -21.1857
    },
    {
      "id": "us6000ta6h",
      "mag": 4.5,
      "place": "Pagan region, Northern Mariana Islands",
      "time": "2026-07-04T22:12:53.394Z",
      "url": "https://earthquake.usgs.gov/earthquakes/eventpage/us6000ta6h",
      "tsunami": false,
      "depth_km": 187.791,
      "lon": 145.7985,
      "lat": 18.8951
    },
    {
      "id": "us6000ta64",
      "mag": 4.7,
      "place": "51 km S of Atico, Peru",
      "time": "2026-07-04T20:24:48.581Z",
      "url": "https://earthquake.usgs.gov/earthquakes/eventpage/us6000ta64",
      "tsunami": false,
      "depth_km": 26.779,
      "lon": -73.5875,
      "lat": -16.6722
    }
  ],
  "significant_week_events": [
    {
      "id": "uw714040221",
      "mag": 3.8,
      "place": "2 km E of Oak Harbor, Washington",
      "time": "2026-07-02T06:35:47.600Z",
      "url": "https://earthquake.usgs.gov/earthquakes/eventpage/uw714040221",
      "tsunami": false,
      "depth_km": 25.38,
      "lon": -122.6065,
      "lat": 48.2888333333333
    },
    {
      "id": "us6000t9bg",
      "mag": 5.3,
      "place": "265 km SSE of Dunhuang, China",
      "time": "2026-06-30T23:44:54.830Z",
      "url": "https://earthquake.usgs.gov/earthquakes/eventpage/us6000t9bg",
      "tsunami": false,
      "depth_km": 10,
      "lon": 95.3273,
      "lat": 37.8295
    }
  ]
}